blaster_core.cp312-win_amd64.pyd
blaster/__init__.py
blaster/app.py
blaster/blaster.py
blaster/interface.py
blaster/lattice_io.py
blaster/size_reduction.py
blaster/stats.py
blaster_python-0.1.1.dist-info/licenses/LICENSE
blaster_python-0.1.1.dist-info/METADATA
blaster_python-0.1.1.dist-info/WHEEL
blaster_python-0.1.1.dist-info/entry_points.txt
blaster_python-0.1.1.dist-info/top_level.txt
blaster_python-0.1.1.dist-info/RECORD
