Metadata-Version: 2.4
Name: blaster-python
Version: 0.1.1
Summary: BLASter: A proof of concept of an LLL-like lattice reduction algorithm with parallelization and segmentation
Author: Leo Ducas, Ludo Pulles, Marc Stevens
License-Expression: MIT
Project-URL: Homepage, https://github.com/ludopulles/BLASter
Project-URL: Repository, https://github.com/ludopulles/BLASter
Project-URL: Issues, https://github.com/ludopulles/BLASter/issues
Classifier: Development Status :: 3 - Alpha
Classifier: Intended Audience :: Science/Research
Classifier: Programming Language :: Python :: 3
Classifier: Programming Language :: Python :: 3.10
Classifier: Programming Language :: Python :: 3.11
Classifier: Programming Language :: Python :: 3.12
Classifier: Programming Language :: Python :: 3.13
Classifier: Programming Language :: Cython
Classifier: Programming Language :: C++
Classifier: Topic :: Scientific/Engineering :: Mathematics
Classifier: Topic :: Security :: Cryptography
Requires-Python: >=3.11
License-File: LICENSE
Requires-Dist: numpy>=1.20
Requires-Dist: cysignals
Requires-Dist: matplotlib
Provides-Extra: dev
Requires-Dist: build; extra == "dev"
Requires-Dist: twine; extra == "dev"
Requires-Dist: pytest; extra == "dev"
Dynamic: license-file
